README.md
setup.py
wishlist/__init__.py
wishlist/__main__.py
wishlist/compat.py
wishlist/core.py
wishlist/environ.py
wishlist/exception.py
wishlist.egg-info/PKG-INFO
wishlist.egg-info/SOURCES.txt
wishlist.egg-info/dependency_links.txt
wishlist.egg-info/entry_points.txt
wishlist.egg-info/requires.txt
wishlist.egg-info/top_level.txt