Metadata-Version: 2.1
Name: wishlist
Version: 0.5.1
Summary: Amazon wishlist scraper
Home-page: http://github.com/Jaymon/wishlist
Author: Jay Marcyes
Author-email: jay@marcyes.com
License: GPLv2+
Platform: UNKNOWN
Classifier: Development Status :: 4 - Beta
Classifier: Environment :: Plugins
Classifier: Intended Audience :: Developers
Classifier: License :: OSI Approved :: GNU General Public License v2 or later (GPLv2+)
Classifier: Operating System :: OS Independent
Classifier: Programming Language :: Python :: 2.7
